angelo/VERSION
angelo/__init__.py
angelo-0.0.1.dist-info/LICENSE
angelo-0.0.1.dist-info/METADATA
angelo-0.0.1.dist-info/WHEEL
angelo-0.0.1.dist-info/top_level.txt
angelo-0.0.1.dist-info/RECORD
