Metadata-Version: 2.1
Name: angelo
Version: 0.0.1
Summary: Angelo
Home-page: https://github.com/benhorsburgh/angelo
Author: Ben Horsburgh
Author-email: 16501406+benhorsburgh@users.noreply.github.com
License: Apache License 2.0
Project-URL: Bug Tracker, https://github.com/benhorsburgh/angelo/issues
Project-URL: Changelog, https://github.com/benhorsburgh/angelo/blob/main/CHANGELOG.md
Keywords: angelo,turtle,logo
Platform: any
Classifier: Programming Language :: Python :: 3.10
Requires-Python: >=3.10
License-File: LICENSE
